migrate_anything/__init__.py
migrate_anything/log.py
migrate_anything/main.py
migrate_anything/migrator.py
migrate_anything/storage/__init__.py
migrate_anything-0.2.0.dist-info/licenses/LICENSE
migrate_anything-0.2.0.dist-info/METADATA
migrate_anything-0.2.0.dist-info/WHEEL
migrate_anything-0.2.0.dist-info/entry_points.txt
migrate_anything-0.2.0.dist-info/top_level.txt
migrate_anything-0.2.0.dist-info/RECORD
