Metadata-Version: 2.4
Name: migrate-anything
Version: 0.2.0
Summary: Helps manage migrations for databases and anything else
Home-page: https://github.com/cocreators-ee/migrate-anything
Author: Cocreators OÜ
Author-email: janne@cocreators.ee
Project-URL: Bug Reports, https://github.com/cocreators-ee/migrate-anything/issues
Project-URL: Source, https://github.com/cocreators-ee/migrate-anything/
Keywords: migrate database db release
Classifier: License :: OSI Approved :: BSD License
Classifier: Programming Language :: Python :: 3
Classifier: Programming Language :: Python :: 3.8
Classifier: Programming Language :: Python :: 3.9
Classifier: Programming Language :: Python :: 3.10
Classifier: Programming Language :: Python :: 3.11
Classifier: Programming Language :: Python :: 3.12
Classifier: Programming Language :: Python :: 3.13
Requires-Python: >=3.6, <4
License-File: LICENSE
Dynamic: author
Dynamic: author-email
Dynamic: classifier
Dynamic: description
Dynamic: description-content-type
Dynamic: home-page
Dynamic: keywords
Dynamic: license-file
Dynamic: project-url
Dynamic: requires-python
Dynamic: summary
